fmtt-0.5.0.dist-info/METADATA
fmtt-0.5.0.dist-info/WHEEL
fmtt/__init__.py
fmtt/_lowlevel.cpython-312-darwin.so
fmtt-0.5.0.dist-info/RECORD
