Metadata-Version: 2.3
Name: fmtt
Version: 0.5.0
Summary: Python binding for ForMaT Text (FMTT)
Author-email: "Steven Hé (Sīchàng)" <stevensichanghe@gmail.com>
License: MIT
Requires-Python: >=3.8
Project-URL: Source Code, https://github.com/SichangHe/fmtt
